{
  "杯子": "cup",
  "水杯": "cup",
  "瓶子": "bottle",
  "水瓶": "bottle",
  "电脑": "laptop",
  "笔记本电脑": "laptop",
  "公交车": "bus",
  "校车": "bus",
  "自行车": "bicycle",
  "键盘": "keyboard",
  "笔记本": "notebook",
  "书": "book",
  "椅子": "chair",
  "座椅": "chair",
  "阅览座": "chair",
  "桌子": "table",
  "桌面": "table",
  "餐桌": "table",
  "人": "person",
  "人物": "person",
  "背包": "backpack",
  "汽车": "car",
  "讲台": "lectern",
  "课桌": "desk",
  "书桌": "desk",
  "投影": "projector",
  "投影仪": "projector",
  "书架": "bookshelf",
  "台灯": "lamp",
  "餐盘": "tray",
  "饮品": "drink",
  "饮料": "drink",
  "食物": "food",
  "道路": "road",
  "路面": "road",
  "建筑": "building",
  "活动物料": "event materials",
  "设备": "laboratory equipment",
  "实验设备": "laboratory equipment",
  "实验器材": "laboratory equipment",
  "实验室设备": "laboratory equipment",
  "屏幕": "screen",
  "电脑屏幕": "screen",
  "显示器": "monitor",
  "工具": "tool"
}